---
layout: post
title:  "Python 系列4: 编译"
date:   2020-03-12 19:40:00
categories: python
---

很多人都认为`Python`是解释型语言，就没有在意过是如何解释，从哪里解释。 首先`py`文件通过编译成`Python`字节码，然后再通过解释器器解释执行，默认会生成一个`pyc`缓存文件，这个文也可以在启动时加入`-B`参数不生成`pyc`文件，所以`pyc`文件不是必须的。

[如何从`pyc`文件中解析字节码](https://stackoverflow.com/questions/32562163/how-can-i-understand-a-pyc-file-content)

```python

> import dis
> import marshal
> f = open("__pycache__/module.cpython-37.pyc", "rb")
> f.read(16)
> code = marshal.load(f)
> dis.dis(code)

  1           0 LOAD_CONST               0 (<code object func at 0x11454b780, file "/py/module.py", line 1>)
              2 LOAD_CONST               1 ('func')
              4 MAKE_FUNCTION            0
              6 STORE_NAME               0 (func)
              8 LOAD_CONST               2 (None)
             10 RETURN_VALUE

Disassembly of <code object func at 0x11454b780, file "/py/module.py", line 1>:
  2           0 LOAD_GLOBAL              0 (print)
              2 LOAD_CONST               1 ('model')
              4 CALL_FUNCTION            1
              6 POP_TOP
              8 LOAD_CONST               0 (None)
             10 RETURN_VALUE

```

